sng/Config.py
sng/Generator.py
sng/__init__.py
sng/builtin_wordlists.py
sng/helpers.py
sng/wordlists.py
sng/wordlists/behemoth.txt
sng/wordlists/black-speech.txt
sng/wordlists/english.txt
sng/wordlists/french.txt
sng/wordlists/gallic.txt
sng/wordlists/german.txt
sng/wordlists/greek.txt
sng/wordlists/latin.txt
sng/wordlists/lorem-ipsum.txt
sng/wordlists/pokemon.txt
sng-0.3.2.dist-info/DESCRIPTION.rst
sng-0.3.2.dist-info/METADATA
sng-0.3.2.dist-info/RECORD
sng-0.3.2.dist-info/WHEEL
sng-0.3.2.dist-info/metadata.json
sng-0.3.2.dist-info/top_level.txt
