Metadata-Version: 2.0
Name: sng
Version: 0.3.2
Summary: Generate name proposals for companies, software, etc.
Home-page: http://github.com/AlexEngelhardt/startup-name-generator
Author: Alexander Engelhardt
Author-email: alexander.w.engelhardt@gmail.com
License: MIT
Platform: UNKNOWN
Classifier: Development Status :: 3 - Alpha
Classifier: Environment :: Console
Classifier: Intended Audience :: Developers
Classifier: License :: OSI Approved :: MIT License
Classifier: Programming Language :: Python :: 3
Classifier: Topic :: Text Processing :: Linguistic
Classifier: Topic :: Utilities
Requires-Dist: pyyaml
Requires-Dist: keras
Requires-Dist: tensorflow
Requires-Dist: numpy
